pygenesig/__init__.py
pygenesig/bioqc.py
pygenesig/clevergini.py
pygenesig/file_formats.py
pygenesig/gini.py
pygenesig/limma.py
pygenesig/mcp_counter.py
pygenesig/perfmeasures.py
pygenesig/rank.py
pygenesig/tools.py
pygenesig/validation.py
pygenesig/visualization.py
pygenesig/tests/__init__.py
pygenesig/tests/test_bioqc.py
pygenesig/tests/test_file_formats.py
pygenesig/tests/test_gini.py
pygenesig/tests/test_mcp_counter.py
pygenesig/tests/test_tools.py
pygenesig/tests/test_validation.py
pygenesig-0.2.2.dist-info/LICENSE
pygenesig-0.2.2.dist-info/METADATA
pygenesig-0.2.2.dist-info/WHEEL
pygenesig-0.2.2.dist-info/top_level.txt
pygenesig-0.2.2.dist-info/RECORD
